simpletool/__init__.py
simpletool/__main__.py
simpletool/errors.py
simpletool/models.py
simpletool/schema.py
simpletool/types.py
simpletool/asyncio/__init__.py
simpletool-0.0.32.dist-info/licenses/LICENSE
simpletool-0.0.32.dist-info/METADATA
simpletool-0.0.32.dist-info/WHEEL
simpletool-0.0.32.dist-info/top_level.txt
simpletool-0.0.32.dist-info/RECORD
